ReallySimpleDB/__init__.py
ReallySimpleDB/manager.py
ReallySimpleDB/utils.py
ReallySimpleDB-1.2.dist-info/METADATA
ReallySimpleDB-1.2.dist-info/WHEEL
ReallySimpleDB-1.2.dist-info/top_level.txt
ReallySimpleDB-1.2.dist-info/RECORD
