Metadata-Version: 2.1
Name: ReallySimpleDB
Version: 1.2
Summary: A tool for easily manage databases with Python
Home-page: https://github.com/truethari/ReallySimpleDB
Author: tharindu.dev
Author-email: tharindu.nm@yahoo.com
License: UNKNOWN
Project-URL: Bug Tracker, https://github.com/truethari/ReallySimpleDB/issues
Keywords: database sqlite python-database python-sqlite database-management
Platform: UNKNOWN
Classifier: Programming Language :: Python :: 3
